ulkey/__init__.py
ulkey/core.py
ulkey/run.py
utils/__init__.py
utils/cli.py
utils/utils.py
ul_key-1.2.1.dist-info/METADATA
ul_key-1.2.1.dist-info/WHEEL
ul_key-1.2.1.dist-info/entry_points.txt
ul_key-1.2.1.dist-info/top_level.txt
ul_key-1.2.1.dist-info/RECORD
