Metadata-Version: 2.4
Name: ul-key
Version: 1.2.1
Summary: UL-Key An indispensable assistant in data encryption.
Home-page: https://example.com/ulkey
Author: starfal8k
Classifier: Programming Language :: Python :: 3
Classifier: Operating System :: OS Independent
Requires-Python: >=3.7
Requires-Dist: click
Dynamic: author
Dynamic: classifier
Dynamic: description
Dynamic: description-content-type
Dynamic: home-page
Dynamic: requires-dist
Dynamic: requires-python
Dynamic: summary
